django_simple_quiz-0.1.1.dist-info/DESCRIPTION.rst
django_simple_quiz-0.1.1.dist-info/METADATA
django_simple_quiz-0.1.1.dist-info/RECORD
django_simple_quiz-0.1.1.dist-info/WHEEL
django_simple_quiz-0.1.1.dist-info/metadata.json
django_simple_quiz-0.1.1.dist-info/top_level.txt
quiz/__init__.py
quiz/abstract_models.py
quiz/admin.py
quiz/apps.py
quiz/forms.py
quiz/managers.py
quiz/models.py
quiz/urls.py
quiz/utils.py
quiz/views.py
quiz/migrations/0001_initial.py
quiz/migrations/__init__.py
quiz/templates/quiz/thankyou.html
quiz/templates/quiz/wizard.html
